setup.cfg
setup.py
bin/create-vault-ca
bin/fetch-ssl-cert
vault_ca/__init__.py
vault_ca.egg-info/PKG-INFO
vault_ca.egg-info/SOURCES.txt
vault_ca.egg-info/dependency_links.txt
vault_ca.egg-info/requires.txt
vault_ca.egg-info/top_level.txt