Metadata-Version: 1.1
Name: vault-ca
Version: 0.3
Summary: Set of utils to create your own CA using hashicorp Vault
Home-page: https://github.com/crisidev/vault-ca
Author: Matteo Bigoi
Author-email: bigo@crisidev.org
License: GPLv3
Download-URL: https://github.com/crisidev/vault-ca/archive/0.3.tar.gz
Keywords: ssl,certificate-authority,vault
Platform: UNKNOWN
Classifier: Development Status :: 3 - Alpha
Classifier: Intended Audience :: Developers
Classifier: Topic :: Internet :: WWW/HTTP :: HTTP Servers
Classifier: License :: OSI Approved :: GNU General Public License v3 (GPLv3)
Classifier: Programming Language :: Unix Shell
Classifier: Programming Language :: Python :: 2
Classifier: Programming Language :: Python :: 2.7
Classifier: Programming Language :: Python :: 3
Classifier: Programming Language :: Python :: 3.4
Classifier: Programming Language :: Python :: 3.4
Classifier: Programming Language :: Python :: 3.5
Classifier: Programming Language :: Python :: 3.6
